Workbook

Sheet Read me
A1: UC15 ERP Data Platform: Source-to-target mapping
A3: Purpose | B3: Shows, for every column in the PostgreSQL data warehouse (uc15_dw), where the data comes from and what is done to it on the way.
A4: Data path | B4: Raw file in datasets/ > cleaned file in silver/cleansing/ > Pentaho transformation > warehouse table.
A5: Sheets | B5: Table summary: one row per table, in load order. Column mapping: one row per column. Relationships: the foreign keys between tables.
A6: How it was produced | B6: Generated from the table definitions (sql/01_create_star_schema.sql), the 15 Pentaho transformations in pentaho/transformations/, and the headers of the raw and cleaned files. It is not typed by hand.
A7: Row counts | B7: The Rows loaded values are the counts that sql/05_reconciliation_checks.sql confirms after each load.
A8: Scope | B8: Covers the 15 warehouse tables. The real-time REST API demo (realtime_rest_demo) and the ETL audit table (etl_run_log) are separate and are not mapped here.
A10: Checks
A11: Tables documented | B11: =COUNTA('Table summary'!B5:B19) -> 15
A12: Columns documented | B12: =COUNTA('Column mapping'!C5:C145) -> 141
A13: Columns counted per table | B13: ='Table summary'!K20 -> 141
A14: Foreign keys listed | B14: =COUNTA(Relationships!B5:B18) -> 14
A15: Counts agree? | B15: =IF(B12=B13,"Yes","CHECK") -> Yes
A17: Legend (Key / constraint)
A18: PK | B18: Primary key of the table
A19: FK to X.y | B19: Foreign key: must match column y in table X
A20: Unique | B20: No two rows can have the same value
A21: Not null | B21: The column cannot be empty

Sheet Column mapping
A1: Source-to-target mapping: every column of every warehouse table
A2: One row per target column. Read left to right: where it comes from (raw file, cleaned file), what was done to it, and how Pentaho loads it.
A4: # | B4: Target table | C4: Target column | D4: Data type | E4: Key / constraint | F4: Source dataset | G4: Raw file (datasets/) | H4: Raw column | I4: Cleaned file (silver/) | J4: Cleaned column | K4: Cleaning applied | L4: Transformation rule (Pentaho) | M4: Pentaho transformation | N4: Notes from the table definition
A5: 1 | B5: DimMonth | C5: month_key | D5: SMALLINT | E5: PK | F5: Month list (generated) | H5: (generated by python/generate_reference_data.py) | I5: silver/cleansing/reference_data/DimMonth.csv | K5: Not applicable | L5: Copied as is. | M5: Load DimMonth.ktr | N5: 1-12, no year (seasonal pattern only)
A6: 2 | B6: DimMonth | C6: month_name | D6: VARCHAR(15) | E6: Not null | F6: Month list (generated) | H6: (generated by python/generate_reference_data.py) | I6: silver/cleansing/reference_data/DimMonth.csv | K6: Not applicable | L6: Copied as is. | M6: Load DimMonth.ktr
A7: 3 | B7: DimDate | C7: date_key | D7: INT | E7: PK | F7: Calendar (generated) | H7: (generated by python/generate_reference_data.py) | I7: silver/cleansing/reference_data/DimDate.csv | K7: Not applicable | L7: Copied as is. | M7: Load DimDate.ktr | N7: format YYYYMMDD
A8: 4 | B8: DimDate | C8: full_date | D8: DATE | E8: Not null | F8: Calendar (generated) | H8: (generated by python/generate_reference_data.py) | I8: silver/cleansing/reference_data/DimDate.csv | K8: Not applicable | L8: Read as a date (yyyy-MM-dd). | M8: Load DimDate.ktr
A9: 5 | B9: DimDate | C9: year | D9: SMALLINT | E9: Not null | F9: Calendar (generated) | H9: (generated by python/generate_reference_data.py) | I9: silver/cleansing/reference_data/DimDate.csv | K9: Not applicable | L9: Copied as is. | M9: Load DimDate.ktr
A10: 6 | B10: DimDate | C10: quarter | D10: SMALLINT | E10: Not null | F10: Calendar (generated) | H10: (generated by python/generate_reference_data.py) | I10: silver/cleansing/reference_data/DimDate.csv | K10: Not applicable | L10: Copied as is. | M10: Load DimDate.ktr
A11: 7 | B11: DimDate | C11: month | D11: SMALLINT | E11: Not null | F11: Calendar (generated) | H11: (generated by python/generate_reference_data.py) | I11: silver/cleansing/reference_data/DimDate.csv | K11: Not applicable | L11: Copied as is. | M11: Load DimDate.ktr
A12: 8 | B12: DimDate | C12: month_name | D12: VARCHAR(15) | E12: Not null | F12: Calendar (generated) | H12: (generated by python/generate_reference_data.py) | I12: silver/cleansing/reference_data/DimDate.csv | K12: Not applicable | L12: Copied as is. | M12: Load DimDate.ktr
A13: 9 | B13: DimDate | C13: day | D13: SMALLINT | E13: Not null | F13: Calendar (generated) | H13: (generated by python/generate_reference_data.py) | I13: silver/cleansing/reference_data/DimDate.csv | K13: Not applicable | L13: Copied as is. | M13: Load DimDate.ktr
A14: 10 | B14: DimDate | C14: day_of_week | D14: SMALLINT | E14: Not null | F14: Calendar (generated) | H14: (generated by python/generate_reference_data.py) | I14: silver/cleansing/reference_data/DimDate.csv | K14: Not applicable | L14: Copied as is. | M14: Load DimDate.ktr | N14: 1=Monday .. 7=Sunday
A15: 11 | B15: DimDate | C15: day_name | D15: VARCHAR(15) | E15: Not null | F15: Calendar (generated) | H15: (generated by python/generate_reference_data.py) | I15: silver/cleansing/reference_data/DimDate.csv | K15: Not applicable | L15: Copied as is. | M15: Load DimDate.ktr
A16: 12 | B16: DimDate | C16: is_weekend | D16: BOOLEAN | E16: Not null | F16: Calendar (generated) | H16: (generated by python/generate_reference_data.py) | I16: silver/cleansing/reference_data/DimDate.csv | K16: Not applicable | L16: Copied as is. | M16: Load DimDate.ktr
A17: 13 | B17: DimDate | C17: week_of_year | D17: SMALLINT | E17: Not null | F17: Calendar (generated) | H17: (generated by python/generate_reference_data.py) | I17: silver/cleansing/reference_data/DimDate.csv | K17: Not applicable | L17: Copied as is. | M17: Load DimDate.ktr
A18: 14 | B18: DimEmployee | C18: employee_key | D18: SERIAL | E18: PK | F18: Employee | G18: datasets/employee_data.xls | H18: (none) | I18: silver/cleansing/cleaned_datasets/employee_data_cleaned.csv | K18: Not applicable | L18: Generated by PostgreSQL: a sequence number (surrogate key). | M18: Load DimEmployee.ktr | N18: generated: source has
A19: 15 | B19: DimEmployee | C19: first_name | D19: VARCHAR(100) | F19: Employee | G19: datasets/employee_data.xls | H19: First Name | I19: silver/cleansing/cleaned_datasets/employee_data_cleaned.csv | J19: first_name | K19: Name standardised (lower case, underscores) | L19: Copied as is. | M19: Load DimEmployee.ktr
A20: 16 | B20: DimEmployee | C20: last_name | D20: VARCHAR(100) | F20: Employee | G20: datasets/employee_data.xls | H20: Last Name | I20: silver/cleansing/cleaned_datasets/employee_data_cleaned.csv | J20: last_name | K20: Name standardised (lower case, underscores) | L20: Copied as is. | M20: Load DimEmployee.ktr
A21: 17 | B21: DimEmployee | C21: gender | D21: VARCHAR(20) | F21: Employee | G21: datasets/employee_data.xls | H21: Gender | I21: silver/cleansing/cleaned_datasets/employee_data_cleaned.csv | J21: gender | K21: Name standardised (lower case, underscores) | L21: Copied as is. | M21: Load DimEmployee.ktr
A22: 18 | B22: DimEmployee | C22: age | D22: SMALLINT | F22: Employee | G22: datasets/employee_data.xls | H22: Age | I22: silver/cleansing/cleaned_datasets/employee_data_cleaned.csv | J22: age | K22: Name standardised (lower case, underscores) | L22: Copied as is. | M22: Load DimEmployee.ktr
A23: 19 | B23: DimEmployee | C23: salary | D23: NUMERIC(12,2) | F23: Employee | G23: datasets/employee_data.xls | H23: Salary | I23: silver/cleansing/cleaned_datasets/employee_data_cleaned.csv | J23: salary | K23: Name standardised (lower case, underscores) | L23: Copied as is. | M23: Load DimEmployee.ktr
A24: 20 | B24: DimEmployee | C24: expenditure | D24: NUMERIC(12,2) | F24: Employee | G24: datasets/employee_data.xls | H24: Expenditure | I24: silver/cleansing/cleaned_datasets/employee_data_cleaned.csv | J24: expenditure | K24: Name standardised (lower case, underscores) | L24: Copied as is. | M24: Load DimEmployee.ktr
A25: 21 | B25: DimEmployee | C25: savings | D25: NUMERIC(12,2) | F25: Employee | G25: datasets/employee_data.xls | H25: Savings | I25: silver/cleansing/cleaned_datasets/employee_data_cleaned.csv | J25: savings | K25: Name standardised (lower case, underscores) | L25: Copied as is. | M25: Load DimEmployee.ktr
A26: 22 | B26: DimEmployee | C26: expenditure_percentage | D26: NUMERIC(6,4) | F26: Employee | G26: datasets/employee_data.xls | H26: Expenditure Percentage | I26: silver/cleansing/cleaned_datasets/employee_data_cleaned.csv | J26: expenditure_percentage | K26: Name standardised (lower case, underscores) | L26: Copied as is. | M26: Load DimEmployee.ktr
A27: 23 | B27: DimEmployee | C27: savings_percentage | D27: NUMERIC(6,4) | F27: Employee | G27: datasets/employee_data.xls | H27: Savings Percentage | I27: silver/cleansing/cleaned_datasets/employee_data_cleaned.csv | J27: savings_percentage | K27: Name standardised (lower case, underscores) | L27: Copied as is. | M27: Load DimEmployee.ktr
A28: 24 | B28: DimAsset | C28: asset_key | D28: SERIAL | E28: PK | F28: Asset | G28: datasets/Asset_data.xml | H28: (none) | I28: silver/cleansing/cleaned_datasets/asset_data_cleaned.csv | K28: Not applicable | L28: Generated by PostgreSQL: a sequence number (surrogate key). | M28: Load DimAsset.ktr
A29: 25 | B29: DimAsset | C29: asset_id | D29: VARCHAR(20) | E29: Unique, Not null | F29: Asset | G29: datasets/Asset_data.xml | H29: asset_id | I29: silver/cleansing/cleaned_datasets/asset_data_cleaned.csv | J29: asset_id | K29: Name unchanged | L29: Copied as is. | M29: Load DimAsset.ktr
A30: 26 | B30: DimAsset | C30: location | D30: VARCHAR(100) | F30: Asset | G30: datasets/Asset_data.xml | H30: location | I30: silver/cleansing/cleaned_datasets/asset_data_cleaned.csv | J30: location | K30: Name unchanged | L30: Copied as is. | M30: Load DimAsset.ktr
A31: 27 | B31: DimAsset | C31: install_year | D31: SMALLINT | F31: Asset | G31: datasets/Asset_data.xml | H31: install_year | I31: silver/cleansing/cleaned_datasets/asset_data_cleaned.csv | J31: install_year | K31: Name unchanged | L31: Copied as is. | M31: Load DimAsset.ktr
A32: 28 | B32: DimAsset | C32: last_maintenance_year | D32: SMALLINT | F32: Asset | G32: datasets/Asset_data.xml | H32: last_maintenance_year | I32: silver/cleansing/cleaned_datasets/asset_data_cleaned.csv | J32: last_maintenance_year | K32: Name unchanged | L32: Copied as is. | M32: Load DimAsset.ktr
A33: 29 | B33: DimAsset | C33: usage_hours_per_month | D33: NUMERIC(10,2) | F33: Asset | G33: datasets/Asset_data.xml | H33: usage_hours_per_month | I33: silver/cleansing/cleaned_datasets/asset_data_cleaned.csv | J33: usage_hours_per_month | K33: Name unchanged | L33: Copied as is. | M33: Load DimAsset.ktr
A34: 30 | B34: DimAsset | C34: failure_count | D34: SMALLINT | F34: Asset | G34: datasets/Asset_data.xml | H34: failure_count | I34: silver/cleansing/cleaned_datasets/asset_data_cleaned.csv | J34: failure_count | K34: Name unchanged | L34: Copied as is. | M34: Load DimAsset.ktr
A35: 31 | B35: DimAsset | C35: condition_score | D35: NUMERIC(6,4) | F35: Asset | G35: datasets/Asset_data.xml | H35: condition_score | I35: silver/cleansing/cleaned_datasets/asset_data_cleaned.csv | J35: condition_score | K35: Name unchanged | L35: Copied as is. | M35: Load DimAsset.ktr
A36: 32 | B36: DimAsset | C36: maintenance_cost_last_year | D36: NUMERIC(12,2) | F36: Asset | G36: datasets/Asset_data.xml | H36: maintenance_cost_last_year | I36: silver/cleansing/cleaned_datasets/asset_data_cleaned.csv | J36: maintenance_cost_last_year | K36: Name unchanged | L36: Copied as is. | M36: Load DimAsset.ktr
A37: 33 | B37: DimAsset | C37: asset_type | D37: VARCHAR(50) | F37: Asset | G37: datasets/Asset_data.xml | H37: asset_type | I37: silver/cleansing/cleaned_datasets/asset_data_cleaned.csv | J37: asset_type | K37: Name unchanged | L37: Copied as is. | M37: Load DimAsset.ktr
A38: 34 | B38: DimAsset | C38: operational_state | D38: VARCHAR(30) | F38: Asset | G38: datasets/Asset_data.xml | H38: operational_state | I38: silver/cleansing/cleaned_datasets/asset_data_cleaned.csv | J38: operational_state | K38: Name unchanged | L38: Copied as is. | M38: Load DimAsset.ktr
A39: 35 | B39: DimAsset | C39: disposal_decision | D39: VARCHAR(30) | F39: Asset | G39: datasets/Asset_data.xml | H39: disposal_decision | I39: silver/cleansing/cleaned_datasets/asset_data_cleaned.csv | J39: disposal_decision | K39: Name unchanged | L39: Copied as is. | M39: Load DimAsset.ktr
A40: 36 | B40: DimSupplier | C40: supplier_key | D40: SERIAL | E40: PK | F40: Procurement | G40: datasets/procurement_all.csv | H40: (none) | I40: silver/cleansing/cleaned_datasets/procurement_all_cleaned.csv | K40: Not applicable | L40: Generated by PostgreSQL: a sequence number (surrogate key). | M40: Load DimSupplier.ktr
A41: 37 | B41: DimSupplier | C41: supplier_id | D41: VARCHAR(20) | E41: Unique, Not null | F41: Procurement | G41: datasets/procurement_all.csv | H41: supplier_id | I41: silver/cleansing/cleaned_datasets/procurement_all_cleaned.csv | J41: supplier_id | K41: Name unchanged | L41: Each different supplier_id in the file is kept once (duplicates removed). | M41: Load DimSupplier.ktr
A42: 38 | B42: DimCustomerMaster | C42: customer_key | D42: SERIAL | E42: PK | F42: Customer Master | G42: datasets/Customer_Master.json | H42: (none) | I42: silver/cleansing/cleaned_datasets/customer_master_cleaned.csv | K42: Not applicable | L42: Generated by PostgreSQL: a sequence number (surrogate key). | M42: Load DimCustomerMaster.ktr
A43: 39 | B43: DimCustomerMaster | C43: customer_id | D43: VARCHAR(20) | E43: Unique, Not null | F43: Customer Master | G43: datasets/Customer_Master.json | H43: customer_id | I43: silver/cleansing/cleaned_datasets/customer_master_cleaned.csv | J43: customer_id | K43: Name unchanged | L43: Copied as is. | M43: Load DimCustomerMaster.ktr
A44: 40 | B44: DimCustomerMaster | C44: customer_name | D44: VARCHAR(150) | F44: Customer Master | G44: datasets/Customer_Master.json | H44: customer_name | I44: silver/cleansing/cleaned_datasets/customer_master_cleaned.csv | J44: customer_name | K44: Name unchanged | L44: Copied as is. | M44: Load DimCustomerMaster.ktr
A45: 41 | B45: DimCustomerMaster | C45: email | D45: VARCHAR(150) | F45: Customer Master | G45: datasets/Customer_Master.json | H45: contact (nested JSON) | I45: silver/cleansing/cleaned_datasets/customer_master_cleaned.csv | J45: contact | K45: Nested JSON kept as JSON text in the cleaned file | L45: Taken from the JSON text in the contact column using the path $.email. | M45: Load DimCustomerMaster.ktr | N45: parsed from source JSON `contact` field
A46: 42 | B46: DimCustomerMaster | C46: phone | D46: VARCHAR(30) | F46: Customer Master | G46: datasets/Customer_Master.json | H46: contact (nested JSON) | I46: silver/cleansing/cleaned_datasets/customer_master_cleaned.csv | J46: contact | K46: Nested JSON kept as JSON text in the cleaned file | L46: Taken from the JSON text in the contact column using the path $.phone. | M46: Load DimCustomerMaster.ktr | N46: parsed from source JSON `contact` field
A47: 43 | B47: DimCustomerMaster | C47: city | D47: VARCHAR(100) | F47: Customer Master | G47: datasets/Customer_Master.json | H47: address (nested JSON) | I47: silver/cleansing/cleaned_datasets/customer_master_cleaned.csv | J47: address | K47: Nested JSON kept as JSON text in the cleaned file | L47: Taken from the JSON text in the address column using the path $.city. | M47: Load DimCustomerMaster.ktr | N47: parsed from source JSON `address` field
A48: 44 | B48: DimCustomerMaster | C48: state | D48: VARCHAR(100) | F48: Customer Master | G48: datasets/Customer_Master.json | H48: address (nested JSON) | I48: silver/cleansing/cleaned_datasets/customer_master_cleaned.csv | J48: address | K48: Nested JSON kept as JSON text in the cleaned file | L48: Taken from the JSON text in the address column using the path $.state. | M48: Load DimCustomerMaster.ktr | N48: parsed from source JSON `address` field
A49: 45 | B49: DimCustomerMaster | C49: country | D49: VARCHAR(100) | F49: Customer Master | G49: datasets/Customer_Master.json | H49: address (nested JSON) | I49: silver/cleansing/cleaned_datasets/customer_master_cleaned.csv | J49: address | K49: Nested JSON kept as JSON text in the cleaned file | L49: Taken from the JSON text in the address column using the path $.country. | M49: Load DimCustomerMaster.ktr | N49: parsed from source JSON `address` field
A50: 46 | B50: DimCustomerMaster | C50: customer_type | D50: VARCHAR(50) | F50: Customer Master | G50: datasets/Customer_Master.json | H50: customer_type | I50: silver/cleansing/cleaned_datasets/customer_master_cleaned.csv | J50: customer_type | K50: Name unchanged | L50: Copied as is. | M50: Load DimCustomerMaster.ktr
A51: 47 | B51: DimCustomerMaster | C51: registration_date | D51: DATE | F51: Customer Master | G51: datasets/Customer_Master.json | H51: registration_date | I51: silver/cleansing/cleaned_datasets/customer_master_cleaned.csv | J51: registration_date | K51: Name unchanged | L51: Read as a date (yyyy-MM-dd). | M51: Load DimCustomerMaster.ktr
A52: 48 | B52: DimCustomerMaster | C52: credit_limit | D52: NUMERIC(14,2) | F52: Customer Master | G52: datasets/Customer_Master.json | H52: credit_limit | I52: silver/cleansing/cleaned_datasets/customer_master_cleaned.csv | J52: credit_limit | K52: Name unchanged | L52: Copied as is. | M52: Load DimCustomerMaster.ktr
A53: 49 | B53: DimCustomerMaster | C53: customer_status | D53: VARCHAR(30) | F53: Customer Master | G53: datasets/Customer_Master.json | H53: customer_status | I53: silver/cleansing/cleaned_datasets/customer_master_cleaned.csv | J53: customer_status | K53: Name unchanged | L53: Copied as is. | M53: Load DimCustomerMaster.ktr
A54: 50 | B54: DimItemInventory | C54: item_key | D54: SERIAL | E54: PK | F54: Inventory | G54: datasets/Inventory_data.json | H54: (none) | I54: silver/cleansing/cleaned_datasets/inventory_data_cleaned.csv | K54: Not applicable | L54: Generated by PostgreSQL: a sequence number (surrogate key). | M54: Load DimItemInventory.ktr
A55: 51 | B55: DimItemInventory | C55: item_id | D55: VARCHAR(20) | E55: Unique, Not null | F55: Inventory | G55: datasets/Inventory_data.json | H55: Item_ID | I55: silver/cleansing/cleaned_datasets/inventory_data_cleaned.csv | J55: item_id | K55: Name standardised (lower case, underscores) | L55: Copied as is. | M55: Load DimItemInventory.ktr
A56: 52 | B56: DimItemInventory | C56: item_name | D56: VARCHAR(150) | F56: Inventory | G56: datasets/Inventory_data.json | H56: Item_Name | I56: silver/cleansing/cleaned_datasets/inventory_data_cleaned.csv | J56: item_name | K56: Name standardised (lower case, underscores) | L56: Copied as is. | M56: Load DimItemInventory.ktr
A57: 53 | B57: DimItemInventory | C57: category | D57: VARCHAR(50) | F57: Inventory | G57: datasets/Inventory_data.json | H57: Category | I57: silver/cleansing/cleaned_datasets/inventory_data_cleaned.csv | J57: category | K57: Name standardised (lower case, underscores) | L57: Copied as is. | M57: Load DimItemInventory.ktr
A58: 54 | B58: DimItemInventory | C58: price_per_unit | D58: NUMERIC(12,2) | F58: Inventory | G58: datasets/Inventory_data.json | H58: Price_Per_Unit | I58: silver/cleansing/cleaned_datasets/inventory_data_cleaned.csv | J58: price_per_unit | K58: Name standardised (lower case, underscores) | L58: Copied as is. | M58: Load DimItemInventory.ktr
A59: 55 | B59: DimWarehouseItem | C59: warehouse_item_key | D59: SERIAL | E59: PK | F59: Warehouse | G59: datasets/warehouse.csv | H59: (none) | I59: silver/cleansing/cleaned_datasets/warehouse_data_cleaned.csv | K59: Not applicable | L59: Generated by PostgreSQL: a sequence number (surrogate key). | M59: Load DimWarehouseItem.ktr
A60: 56 | B60: DimWarehouseItem | C60: item_id | D60: VARCHAR(20) | E60: Unique, Not null | F60: Warehouse | G60: datasets/warehouse.csv | H60: item_id | I60: silver/cleansing/cleaned_datasets/warehouse_data_cleaned.csv | J60: item_id | K60: Name unchanged | L60: Copied as is. | M60: Load DimWarehouseItem.ktr
A61: 57 | B61: DimWarehouseItem | C61: category | D61: VARCHAR(50) | F61: Warehouse | G61: datasets/warehouse.csv | H61: category | I61: silver/cleansing/cleaned_datasets/warehouse_data_cleaned.csv | J61: category | K61: Name unchanged | L61: Copied as is. | M61: Load DimWarehouseItem.ktr
A62: 58 | B62: DimWarehouseItem | C62: storage_location_id | D62: VARCHAR(30) | F62: Warehouse | G62: datasets/warehouse.csv | H62: storage_location_id | I62: silver/cleansing/cleaned_datasets/warehouse_data_cleaned.csv | J62: storage_location_id | K62: Name unchanged | L62: Copied as is. | M62: Load DimWarehouseItem.ktr
A63: 59 | B63: DimWarehouseItem | C63: zone | D63: VARCHAR(30) | F63: Warehouse | G63: datasets/warehouse.csv | H63: zone | I63: silver/cleansing/cleaned_datasets/warehouse_data_cleaned.csv | J63: zone | K63: Name unchanged | L63: Copied as is. | M63: Load DimWarehouseItem.ktr
A64: 60 | B64: FactSales | C64: sales_key | D64: SERIAL | E64: PK | F64: Sales | G64: datasets/Sales_data.csv | H64: (none) | I64: silver/cleansing/cleaned_datasets/sales_data_cleaned.csv | K64: Not applicable | L64: Generated by PostgreSQL: a sequence number (surrogate key). | M64: Load FactSales.ktr
A65: 61 | B65: FactSales | C65: transaction_id | D65: VARCHAR(20) | E65: Unique, Not null | F65: Sales | G65: datasets/Sales_data.csv | H65: Transaction ID | I65: silver/cleansing/cleaned_datasets/sales_data_cleaned.csv | J65: transaction_id | K65: Name standardised (lower case, underscores) | L65: Copied as is. | M65: Load FactSales.ktr
A66: 62 | B66: FactSales | C66: date_key | D66: INT | E66: Not null, FK to DimDate.date_key | F66: Sales | G66: datasets/Sales_data.csv | H66: Date | I66: silver/cleansing/cleaned_datasets/sales_data_cleaned.csv | J66: date | K66: Name standardised (lower case, underscores) | L66: Date converted to text yyyyMMdd, then to an integer. Joins to DimDate.date_key. | M66: Load FactSales.ktr
A67: 63 | B67: FactSales | C67: customer_id | D67: VARCHAR(20) | F67: Sales | G67: datasets/Sales_data.csv | H67: Customer ID | I67: silver/cleansing/cleaned_datasets/sales_data_cleaned.csv | J67: customer_id | K67: Name standardised (lower case, underscores) | L67: Copied as is. | M67: Load FactSales.ktr | N67: degenerate: does not match any other module
A68: 64 | B68: FactSales | C68: gender | D68: VARCHAR(20) | F68: Sales | G68: datasets/Sales_data.csv | H68: Gender | I68: silver/cleansing/cleaned_datasets/sales_data_cleaned.csv | J68: gender | K68: Name standardised (lower case, underscores) | L68: Copied as is. | M68: Load FactSales.ktr
A69: 65 | B69: FactSales | C69: age | D69: SMALLINT | F69: Sales | G69: datasets/Sales_data.csv | H69: Age | I69: silver/cleansing/cleaned_datasets/sales_data_cleaned.csv | J69: age | K69: Name standardised (lower case, underscores) | L69: Copied as is. | M69: Load FactSales.ktr
A70: 66 | B70: FactSales | C70: product_category | D70: VARCHAR(50) | F70: Sales | G70: datasets/Sales_data.csv | H70: Product Category | I70: silver/cleansing/cleaned_datasets/sales_data_cleaned.csv | J70: product_category | K70: Name standardised (lower case, underscores) | L70: Copied as is. | M70: Load FactSales.ktr | N70: degenerate: no product master exists
A71: 67 | B71: FactSales | C71: quantity | D71: INT | F71: Sales | G71: datasets/Sales_data.csv | H71: Quantity | I71: silver/cleansing/cleaned_datasets/sales_data_cleaned.csv | J71: quantity | K71: Name standardised (lower case, underscores) | L71: Copied as is. | M71: Load FactSales.ktr
A72: 68 | B72: FactSales | C72: price_per_unit | D72: NUMERIC(12,2) | F72: Sales | G72: datasets/Sales_data.csv | H72: Price per Unit | I72: silver/cleansing/cleaned_datasets/sales_data_cleaned.csv | J72: price_per_unit | K72: Name standardised (lower case, underscores) | L72: Copied as is. | M72: Load FactSales.ktr
A73: 69 | B73: FactSales | C73: total_amount | D73: NUMERIC(14,2) | F73: Sales | G73: datasets/Sales_data.csv | H73: Total Amount | I73: silver/cleansing/cleaned_datasets/sales_data_cleaned.csv | J73: total_amount | K73: Name standardised (lower case, underscores) | L73: Copied as is. | M73: Load FactSales.ktr
A74: 70 | B74: FactSales | C74: daily_percent_change | D74: NUMERIC(10,6) | F74: Sales | G74: datasets/Sales_data.csv | H74: Daily Percent Change | I74: silver/cleansing/cleaned_datasets/sales_data_cleaned.csv | J74: daily_percent_change | K74: Name standardised (lower case, underscores) | L74: Copied as is. | M74: Load FactSales.ktr
A75: 71 | B75: FactFinance | C75: finance_key | D75: SERIAL | E75: PK | F75: Finance | G75: datasets/Finance_data.csv | H75: (none) | I75: silver/cleansing/cleaned_datasets/finance_data_cleaned.csv | K75: Not applicable | L75: Generated by PostgreSQL: a sequence number (surrogate key). | M75: Load FactFinance.ktr
A76: 72 | B76: FactFinance | C76: transaction_id | D76: VARCHAR(20) | E76: Unique, Not null | F76: Finance | G76: datasets/Finance_data.csv | H76: Transaction ID | I76: silver/cleansing/cleaned_datasets/finance_data_cleaned.csv | J76: transaction_id | K76: Name standardised (lower case, underscores) | L76: Copied as is. | M76: Load FactFinance.ktr
A77: 73 | B77: FactFinance | C77: date_key | D77: INT | E77: Not null, FK to DimDate.date_key | F77: Finance | G77: datasets/Finance_data.csv | H77: Date | I77: silver/cleansing/cleaned_datasets/finance_data_cleaned.csv | J77: date | K77: Name standardised (lower case, underscores) | L77: Date converted to text yyyyMMdd, then to an integer. Joins to DimDate.date_key. | M77: Load FactFinance.ktr
A78: 74 | B78: FactFinance | C78: account_type | D78: VARCHAR(50) | F78: Finance | G78: datasets/Finance_data.csv | H78: Account Type | I78: silver/cleansing/cleaned_datasets/finance_data_cleaned.csv | J78: account_type | K78: Name standardised (lower case, underscores) | L78: Copied as is. | M78: Load FactFinance.ktr
A79: 75 | B79: FactFinance | C79: transaction_amount | D79: NUMERIC(14,2) | F79: Finance | G79: datasets/Finance_data.csv | H79: Transaction Amount | I79: silver/cleansing/cleaned_datasets/finance_data_cleaned.csv | J79: transaction_amount | K79: Name standardised (lower case, underscores) | L79: Copied as is. | M79: Load FactFinance.ktr
A80: 76 | B80: FactFinance | C80: cash_flow | D80: NUMERIC(14,2) | F80: Finance | G80: datasets/Finance_data.csv | H80: Cash Flow | I80: silver/cleansing/cleaned_datasets/finance_data_cleaned.csv | J80: cash_flow | K80: Name standardised (lower case, underscores) | L80: Copied as is. | M80: Load FactFinance.ktr
A81: 77 | B81: FactFinance | C81: net_income | D81: NUMERIC(14,2) | F81: Finance | G81: datasets/Finance_data.csv | H81: Net Income | I81: silver/cleansing/cleaned_datasets/finance_data_cleaned.csv | J81: net_income | K81: Name standardised (lower case, underscores) | L81: Copied as is. | M81: Load FactFinance.ktr
A82: 78 | B82: FactFinance | C82: revenue | D82: NUMERIC(14,2) | F82: Finance | G82: datasets/Finance_data.csv | H82: Revenue | I82: silver/cleansing/cleaned_datasets/finance_data_cleaned.csv | J82: revenue | K82: Name standardised (lower case, underscores) | L82: Copied as is. | M82: Load FactFinance.ktr
A83: 79 | B83: FactFinance | C83: expenditure | D83: NUMERIC(14,2) | F83: Finance | G83: datasets/Finance_data.csv | H83: Expenditure | I83: silver/cleansing/cleaned_datasets/finance_data_cleaned.csv | J83: expenditure | K83: Name standardised (lower case, underscores) | L83: Copied as is. | M83: Load FactFinance.ktr
A84: 80 | B84: FactFinance | C84: profit_margin | D84: NUMERIC(8,4) | F84: Finance | G84: datasets/Finance_data.csv | H84: Profit Margin | I84: silver/cleansing/cleaned_datasets/finance_data_cleaned.csv | J84: profit_margin | K84: Name standardised (lower case, underscores) | L84: Copied as is. | M84: Load FactFinance.ktr
A85: 81 | B85: FactFinance | C85: gross_profit | D85: NUMERIC(14,2) | F85: Finance | G85: datasets/Finance_data.csv | H85: Gross Profit | I85: silver/cleansing/cleaned_datasets/finance_data_cleaned.csv | J85: gross_profit | K85: Name standardised (lower case, underscores) | L85: Copied as is. | M85: Load FactFinance.ktr
A86: 82 | B86: FactFinance | C86: transaction_volume | D86: NUMERIC(14,2) | F86: Finance | G86: datasets/Finance_data.csv | H86: Transaction Volume | I86: silver/cleansing/cleaned_datasets/finance_data_cleaned.csv | J86: transaction_volume | K86: Name standardised (lower case, underscores) | L86: Copied as is. | M86: Load FactFinance.ktr
A87: 83 | B87: FactFinance | C87: accuracy_score | D87: NUMERIC(6,4) | F87: Finance | G87: datasets/Finance_data.csv | H87: Accuracy Score | I87: silver/cleansing/cleaned_datasets/finance_data_cleaned.csv | J87: accuracy_score | K87: Name standardised (lower case, underscores) | L87: Copied as is. | M87: Load FactFinance.ktr
A88: 84 | B88: FactManufacturing | C88: job_key | D88: SERIAL | E88: PK | F88: Manufacturing | G88: datasets/Manufacturing_data.xml | H88: (none) | I88: silver/cleansing/cleaned_datasets/manufacturing_data_cleaned.csv | K88: Not applicable | L88: Generated by PostgreSQL: a sequence number (surrogate key). | M88: Load FactManufacturing.ktr
A89: 85 | B89: FactManufacturing | C89: job_id | D89: VARCHAR(20) | E89: Unique, Not null | F89: Manufacturing | G89: datasets/Manufacturing_data.xml | H89: Job_ID | I89: silver/cleansing/cleaned_datasets/manufacturing_data_cleaned.csv | J89: job_id | K89: Name standardised (lower case, underscores) | L89: Copied as is. | M89: Load FactManufacturing.ktr
A90: 86 | B90: FactManufacturing | C90: scheduled_start_date_key | D90: INT | E90: Not null, FK to DimDate.date_key | F90: Manufacturing | G90: datasets/Manufacturing_data.xml | H90: Scheduled_Start | I90: silver/cleansing/cleaned_datasets/manufacturing_data_cleaned.csv | J90: scheduled_start | K90: Name standardised (lower case, underscores) | L90: Date converted to text yyyyMMdd, then to an integer. Joins to DimDate.date_key. | M90: Load FactManufacturing.ktr
A91: 87 | B91: FactManufacturing | C91: actual_start_date_key | D91: INT | E91: FK to DimDate.date_key | F91: Manufacturing | G91: datasets/Manufacturing_data.xml | H91: Actual_Start | I91: silver/cleansing/cleaned_datasets/manufacturing_data_cleaned.csv | J91: actual_start | K91: Name standardised (lower case, underscores) | L91: Date converted to text yyyyMMdd, then to an integer. Joins to DimDate.date_key. Empty when the source date is empty. | M91: Load FactManufacturing.ktr | N91: NULLABLE:
A92: 88 | B92: FactManufacturing | C92: machine_id | D92: VARCHAR(20) | F92: Manufacturing | G92: datasets/Manufacturing_data.xml | H92: Machine_ID | I92: silver/cleansing/cleaned_datasets/manufacturing_data_cleaned.csv | J92: machine_id | K92: Name standardised (lower case, underscores) | L92: Copied as is. | M92: Load FactManufacturing.ktr | N92: degenerate: only 5 distinct
A93: 89 | B93: FactManufacturing | C93: operation_type | D93: VARCHAR(50) | F93: Manufacturing | G93: datasets/Manufacturing_data.xml | H93: Operation_Type | I93: silver/cleansing/cleaned_datasets/manufacturing_data_cleaned.csv | J93: operation_type | K93: Name standardised (lower case, underscores) | L93: Copied as is. | M93: Load FactManufacturing.ktr
A94: 90 | B94: FactManufacturing | C94: job_status | D94: VARCHAR(30) | F94: Manufacturing | G94: datasets/Manufacturing_data.xml | H94: Job_Status | I94: silver/cleansing/cleaned_datasets/manufacturing_data_cleaned.csv | J94: job_status | K94: Name standardised (lower case, underscores) | L94: Copied as is. | M94: Load FactManufacturing.ktr
A95: 91 | B95: FactManufacturing | C95: optimization_category | D95: VARCHAR(50) | F95: Manufacturing | G95: datasets/Manufacturing_data.xml | H95: Optimization_Category | I95: silver/cleansing/cleaned_datasets/manufacturing_data_cleaned.csv | J95: optimization_category | K95: Name standardised (lower case, underscores) | L95: Copied as is. | M95: Load FactManufacturing.ktr
A96: 92 | B96: FactManufacturing | C96: material_used | D96: NUMERIC(10,2) | F96: Manufacturing | G96: datasets/Manufacturing_data.xml | H96: Material_Used | I96: silver/cleansing/cleaned_datasets/manufacturing_data_cleaned.csv | J96: material_used | K96: Name standardised (lower case, underscores) | L96: Copied as is. | M96: Load FactManufacturing.ktr
A97: 93 | B97: FactManufacturing | C97: processing_time | D97: NUMERIC(10,2) | F97: Manufacturing | G97: datasets/Manufacturing_data.xml | H97: Processing_Time | I97: silver/cleansing/cleaned_datasets/manufacturing_data_cleaned.csv | J97: processing_time | K97: Name standardised (lower case, underscores) | L97: Copied as is. | M97: Load FactManufacturing.ktr
A98: 94 | B98: FactManufacturing | C98: energy_consumption | D98: NUMERIC(10,2) | F98: Manufacturing | G98: datasets/Manufacturing_data.xml | H98: Energy_Consumption | I98: silver/cleansing/cleaned_datasets/manufacturing_data_cleaned.csv | J98: energy_consumption | K98: Name standardised (lower case, underscores) | L98: Copied as is. | M98: Load FactManufacturing.ktr
A99: 95 | B99: FactManufacturing | C99: machine_availability | D99: NUMERIC(6,2) | F99: Manufacturing | G99: datasets/Manufacturing_data.xml | H99: Machine_Availability | I99: silver/cleansing/cleaned_datasets/manufacturing_data_cleaned.csv | J99: machine_availability | K99: Name standardised (lower case, underscores) | L99: Copied as is. | M99: Load FactManufacturing.ktr
A100: 96 | B100: FactAccountsReceivable | C100: ar_key | D100: SERIAL | E100: PK | F100: Account (Accounts Receivable) | G100: datasets/Account_data.xls | H100: (none) | I100: silver/cleansing/cleaned_datasets/account_data_cleaned.csv | K100: Not applicable | L100: Generated by PostgreSQL: a sequence number (surrogate key). | M100: Load FactAccountsReceivable.ktr
A101: 97 | B101: FactAccountsReceivable | C101: document_no | D101: VARCHAR(20) | E101: Unique, Not null | F101: Account (Accounts Receivable) | G101: datasets/Account_data.xls | H101: Document_No | I101: silver/cleansing/cleaned_datasets/account_data_cleaned.csv | J101: document_no | K101: Name standardised (lower case, underscores) | L101: Copied as is. | M101: Load FactAccountsReceivable.ktr
...

Sheet Table summary
A1: Table summary: the 15 warehouse tables in the order the Pentaho job loads them
A2: Rows loaded are the counts confirmed by sql/05_reconciliation_checks.sql. Columns is a formula that counts the rows of the Column mapping sheet.
A4: Load order | B4: Target table | C4: Type | D4: One row is | E4: Source dataset | F4: Raw file (datasets/) | G4: Cleaned file (silver/) | H4: Pentaho transformation | I4: Depends on (loaded first) | J4: Rows loaded | K4: Columns | L4: Cleaning applied in the Silver layer
A5: 1 | B5: DimMonth | C5: Dimension | D5: One month of the year (1 to 12) | E5: Month list (generated) | F5: (generated by python/generate_reference_data.py) | G5: silver/cleansing/reference_data/DimMonth.csv | H5: Load DimMonth.ktr | I5: None | J5: 12 | K5: =COUNTIF('Column mapping'!$B$5:$B$145,B5) -> 2 | L5: Calendar generated by a script; not from a source system
A6: 2 | B6: DimDate | C6: Dimension | D6: One calendar day, 2011-01-01 to 2027-12-31 | E6: Calendar (generated) | F6: (generated by python/generate_reference_data.py) | G6: silver/cleansing/reference_data/DimDate.csv | H6: Load DimDate.ktr | I6: None | J6: 6209 | K6: =COUNTIF('Column mapping'!$B$5:$B$145,B6) -> 11 | L6: Calendar generated by a script; not from a source system
A7: 3 | B7: DimEmployee | C7: Dimension | D7: One employee | E7: Employee | F7: datasets/employee_data.xls | G7: silver/cleansing/cleaned_datasets/employee_data_cleaned.csv | H7: Load DimEmployee.ktr | I7: None | J7: 35 | K7: =COUNTIF('Column mapping'!$B$5:$B$145,B7) -> 10 | L7: Names standardised; types converted; no rows removed
A8: 4 | B8: DimAsset | C8: Dimension | D8: One piece of equipment | E8: Asset | F8: datasets/Asset_data.xml | G8: silver/cleansing/cleaned_datasets/asset_data_cleaned.csv | H8: Load DimAsset.ktr | I8: None | J8: 1245 | K8: =COUNTIF('Column mapping'!$B$5:$B$145,B8) -> 12 | L8: Names standardised; types converted; no rows removed
A9: 5 | B9: DimSupplier | C9: Dimension | D9: One supplier (ID only) | E9: Procurement | F9: datasets/procurement_all.csv | G9: silver/cleansing/cleaned_datasets/procurement_all_cleaned.csv | H9: Load DimSupplier.ktr | I9: None | J9: 10 | K9: =COUNTIF('Column mapping'!$B$5:$B$145,B9) -> 2 | L9: Names standardised; types converted; no rows removed
A10: 6 | B10: DimCustomerMaster | C10: Dimension | D10: One customer | E10: Customer Master | F10: datasets/Customer_Master.json | G10: silver/cleansing/cleaned_datasets/customer_master_cleaned.csv | H10: Load DimCustomerMaster.ktr | I10: None | J10: 1500 | K10: =COUNTIF('Column mapping'!$B$5:$B$145,B10) -> 12 | L10: Names standardised; nested contact and address kept as JSON text; no rows removed
A11: 7 | B11: DimItemInventory | C11: Dimension | D11: One inventory item | E11: Inventory | F11: datasets/Inventory_data.json | G11: silver/cleansing/cleaned_datasets/inventory_data_cleaned.csv | H11: Load DimItemInventory.ktr | I11: None | J11: 1000 | K11: =COUNTIF('Column mapping'!$B$5:$B$145,B11) -> 5 | L11: Names standardised; types converted; no rows removed
A12: 8 | B12: DimWarehouseItem | C12: Dimension | D12: One warehouse item | E12: Warehouse | F12: datasets/warehouse.csv | G12: silver/cleansing/cleaned_datasets/warehouse_data_cleaned.csv | H12: Load DimWarehouseItem.ktr | I12: None | J12: 3204 | K12: =COUNTIF('Column mapping'!$B$5:$B$145,B12) -> 5 | L12: Exact duplicate rows removed (6,408 raw rows became 3,204)
A13: 9 | B13: FactSales | C13: Fact | D13: One sales transaction | E13: Sales | F13: datasets/Sales_data.csv | G13: silver/cleansing/cleaned_datasets/sales_data_cleaned.csv | H13: Load FactSales.ktr | I13: DimDate | J13: 1000 | K13: =COUNTIF('Column mapping'!$B$5:$B$145,B13) -> 11 | L13: Dates converted from DD-MM-YYYY to YYYY-MM-DD; names standardised; no rows removed
A14: 10 | B14: FactFinance | C14: Fact | D14: One finance transaction | E14: Finance | F14: datasets/Finance_data.csv | G14: silver/cleansing/cleaned_datasets/finance_data_cleaned.csv | H14: Load FactFinance.ktr | I14: DimDate | J14: 1000 | K14: =COUNTIF('Column mapping'!$B$5:$B$145,B14) -> 13 | L14: Names standardised; types converted; no rows removed
A15: 11 | B15: FactManufacturing | C15: Fact | D15: One production job | E15: Manufacturing | F15: datasets/Manufacturing_data.xml | G15: silver/cleansing/cleaned_datasets/manufacturing_data_cleaned.csv | H15: Load FactManufacturing.ktr | I15: DimDate | J15: 1000 | K15: =COUNTIF('Column mapping'!$B$5:$B$145,B15) -> 12 | L15: Names standardised; dates converted; no rows removed
A16: 12 | B16: FactAccountsReceivable | C16: Fact | D16: One receivable document | E16: Account (Accounts Receivable) | F16: datasets/Account_data.xls | G16: silver/cleansing/cleaned_datasets/account_data_cleaned.csv | H16: Load FactAccountsReceivable.ktr | I16: DimDate | J16: 45839 | K16: =COUNTIF('Column mapping'!$B$5:$B$145,B16) -> 14 | L16: Names standardised; dates converted to YYYY-MM-DD; no rows removed
... A19: 15 | B19: FactInventoryDemand | C19: Fact | D19: One inventory item in one month | E19: Inventory | F19: datasets/Inventory_data.json | G19: silver/cleansing/cleaned_datasets/inventory_data_cleaned.csv | H19: Load FactInventoryDemand.ktr | I19: DimItemInventory, DimMonth | J19: 12000 | K19: =COUNTIF('Column mapping'!$B$5:$B$145,B19) -> 3 | L19: Names standardised; types converted; no rows removed
B20: Total | J20: =SUM(J5:J19) -> 78558 | K20: =SUM(K5:K19) -> 141

Sheet Relationships
A1: Relationships: foreign keys between the warehouse tables
A2: From the table definition (sql/01_create_star_schema.sql). Each row says: this column must match a key in another table.
A4: # | B4: Fact / table | C4: Column | D4: References table | E4: References column | F4: Can be empty?
A5: 1 | B5: FactSales | C5: date_key | D5: DimDate | E5: date_key | F5: No
A6: 2 | B6: FactFinance | C6: date_key | D6: DimDate | E6: date_key | F6: No
A7: 3 | B7: FactManufacturing | C7: scheduled_start_date_key | D7: DimDate | E7: date_key | F7: No
A8: 4 | B8: FactManufacturing | C8: actual_start_date_key | D8: DimDate | E8: date_key | F8: Yes
A9: 5 | B9: FactAccountsReceivable | C9: doc_date_key | D9: DimDate | E9: date_key | F9: No
A10: 6 | B10: FactAccountsReceivable | C10: net_due_date_key | D10: DimDate | E10: date_key | F10: Yes
A11: 7 | B11: FactAccountsReceivable | C11: clearing_date_key | D11: DimDate | E11: date_key | F11: Yes
A12: 8 | B12: FactProcurement | C12: order_date_key | D12: DimDate | E12: date_key | F12: No
A13: 9 | B13: FactProcurement | C13: expected_delivery_date_key | D13: DimDate | E13: date_key | F13: Yes
A14: 10 | B14: FactProcurement | C14: supplier_key | D14: DimSupplier | E14: supplier_key | F14: No
A15: 11 | B15: FactWarehouseSnapshot | C15: date_key | D15: DimDate | E15: date_key | F15: No
A16: 12 | B16: FactWarehouseSnapshot | C16: warehouse_item_key | D16: DimWarehouseItem | E16: warehouse_item_key | F16: No
... A18: 14 | B18: FactInventoryDemand | C18: month_key | D18: DimMonth | E18: month_key | F18: No
